vtg/__init__.py
vtg/__main__.py
vtg/client.py
vtg/encryption.py
vtg/test.py
vtg/util.py
VANTAGE6_pyClient-0.1.0a1.dist-info/METADATA
VANTAGE6_pyClient-0.1.0a1.dist-info/WHEEL
VANTAGE6_pyClient-0.1.0a1.dist-info/top_level.txt
VANTAGE6_pyClient-0.1.0a1.dist-info/RECORD
