Metadata-Version: 2.1
Name: VANTAGE6-pyClient
Version: 0.1.0a1
Summary: Utilities for federated learning
Home-page: https://github.com/iknl/VANTAGE6-pyClient
License: UNKNOWN
Platform: UNKNOWN
Requires-Python: >=3
Requires-Dist: cryptography
Requires-Dist: requests
Requires-Dist: pyjwt
